nucdraw/__init__.py
nucdraw/core.py
nucdraw/utils.py
nucdraw-0.1.2.dist-info/licenses/LICENSE
nucdraw-0.1.2.dist-info/METADATA
nucdraw-0.1.2.dist-info/WHEEL
nucdraw-0.1.2.dist-info/top_level.txt
nucdraw-0.1.2.dist-info/RECORD
