Metadata-Version: 2.4
Name: nucdraw
Version: 0.1.2
Summary: Draw nucleic acid structures
Author-email: Marco Todisco <marco.todisco.92@gmail.com>
Project-URL: Homepage, https://github.com/mtod92/NucDraw
Requires-Python: >=3.7
License-File: LICENSE
Requires-Dist: matplotlib
Requires-Dist: numpy
Requires-Dist: viennarna
Dynamic: license-file
